pydantic_external_settings/__init__.py
pydantic_external_settings/external_config.py
pydantic_external_settings_v1-0.0.1.dist-info/LICENSE
pydantic_external_settings_v1-0.0.1.dist-info/METADATA
pydantic_external_settings_v1-0.0.1.dist-info/WHEEL
pydantic_external_settings_v1-0.0.1.dist-info/top_level.txt
pydantic_external_settings_v1-0.0.1.dist-info/RECORD
