Metadata-Version: 2.1
Name: pydantic_external_settings_v1
Version: 0.0.1
Summary: provide a class descriptor for pydantic to load settings from external sources.compatible with pydantic 1.x
Home-page: 
Author: zhangxiaojia
Author-email: zhangxiaojia002@ke.com
Platform: any
Classifier: Programming Language :: Python :: 3.5
License-File: LICENSE
Requires-Dist: pydantic ==1.*
